{
  "stories": [
    {
      "id": "US-101",
      "title": "Workspace migration: create workspaces table and add workspace_id to boards",
      "phase": "PHASE-001",
      "dependencies": [],
      "status": "done",
      "acceptance_criteria": [
        "workspaces table exists with id, name, owner_id, created_at columns",
        "boards table has workspace_id foreign key column",
        "migration runs without errors"
      ]
    },
    {
      "id": "US-102",
      "title": "Workspace entity, repository, and service (create, read, delete)",
      "phase": "PHASE-001",
      "dependencies": [
        "US-101"
      ],
      "status": "done",
      "acceptance_criteria": [
        "Workspace JPA entity mapped to workspaces table",
        "WorkspaceRepository extends JpaRepository",
        "WorkspaceService has create, findById, delete methods",
        "Unit tests pass for service layer"
      ]
    },
    {
      "id": "US-103",
      "title": "Workspace membership: add/remove members API",
      "phase": "PHASE-001",
      "dependencies": [
        "US-102"
      ],
      "status": "done",
      "acceptance_criteria": [
        "POST /api/v1/workspaces/{id}/members adds a member",
        "DELETE /api/v1/workspaces/{id}/members/{userId} removes a member",
        "Returns 404 if workspace not found",
        "Returns 403 if caller is not workspace owner"
      ]
    },
    {
      "id": "US-104",
      "title": "Assign board to workspace: update board creation and board response",
      "phase": "PHASE-001",
      "dependencies": [
        "US-102"
      ],
      "status": "done",
      "acceptance_criteria": [
        "Board creation accepts workspaceId in request body",
        "BoardResponse includes workspaceId field",
        "Boards without workspace return null workspaceId"
      ]
    },
    {
      "id": "US-201",
      "title": "Migration: add card_assignees join table and start_date column",
      "phase": "PHASE-002",
      "dependencies": [
        "US-101"
      ],
      "status": "done",
      "acceptance_criteria": [
        "card_assignees join table created with card_id and user_id columns",
        "cards table has start_date column of type DATE",
        "Migration runs without errors"
      ]
    },
    {
      "id": "US-202",
      "title": "Card model and CardResponse: replace assigneeId with assignees list and add startDate",
      "phase": "PHASE-002",
      "dependencies": [
        "US-201"
      ],
      "status": "done",
      "acceptance_criteria": [
        "Card entity has ManyToMany relationship to User via card_assignees",
        "CardResponse replaces assigneeId with List<UserSummary> assignees",
        "CardResponse includes startDate field",
        "Existing card endpoints return updated response shape"
      ]
    },
    {
      "id": "US-203",
      "title": "Add/remove assignee API endpoints on cards",
      "phase": "PHASE-002",
      "dependencies": [
        "US-202"
      ],
      "status": "done",
      "acceptance_criteria": [
        "POST /api/v1/cards/{id}/assignees adds a user as assignee",
        "DELETE /api/v1/cards/{id}/assignees/{userId} removes assignee",
        "Returns 404 if card or user not found",
        "Returns 409 if user already assigned"
      ]
    },
    {
      "id": "US-204",
      "title": "Update card startDate via PATCH card endpoint",
      "phase": "PHASE-002",
      "dependencies": [
        "US-202"
      ],
      "status": "done",
      "acceptance_criteria": [
        "PATCH /api/v1/cards/{id} accepts startDate field",
        "startDate persisted and returned in CardResponse",
        "startDate can be set to null to clear it"
      ]
    },
    {
      "id": "US-301",
      "title": "Attachment migration: create attachments table",
      "phase": "PHASE-003",
      "dependencies": [
        "US-201"
      ],
      "status": "done",
      "acceptance_criteria": [
        "attachments table created with id, card_id, filename, url, uploaded_by, created_at columns",
        "card_id is a foreign key to cards table",
        "Migration runs without errors"
      ]
    },
    {
      "id": "US-302",
      "title": "Attachment upload API: POST /api/v1/cards/{id}/attachments",
      "phase": "PHASE-003",
      "dependencies": [
        "US-301"
      ],
      "status": "done",
      "acceptance_criteria": [
        "POST /api/v1/cards/{id}/attachments accepts multipart/form-data",
        "File stored and URL persisted in attachments table",
        "Returns AttachmentResponse with id, filename, url, uploadedAt",
        "Returns 404 if card not found"
      ]
    },
    {
      "id": "US-401",
      "title": "Board stars migration: create board_stars table",
      "phase": "PHASE-004",
      "dependencies": [
        "US-101"
      ],
      "status": "done",
      "acceptance_criteria": [
        "board_stars table created with user_id and board_id columns",
        "Composite primary key on (user_id, board_id)",
        "Migration runs without errors"
      ]
    },
    {
      "id": "US-402",
      "title": "Board star/unstar API and starred board list endpoint",
      "phase": "PHASE-004",
      "dependencies": [
        "US-401"
      ],
      "status": "done",
      "acceptance_criteria": [
        "POST /api/v1/boards/{id}/star stars the board for current user",
        "DELETE /api/v1/boards/{id}/star unstars the board",
        "GET /api/v1/me/starred-boards returns list of starred boards",
        "Returns 404 if board not found"
      ]
    },
    {
      "id": "US-501",
      "title": "Inbox API: GET /api/v1/me/inbox — cards assigned to current user across all boards",
      "phase": "PHASE-005",
      "dependencies": [
        "US-203"
      ],
      "status": "done",
      "acceptance_criteria": [
        "GET /api/v1/me/inbox returns all cards where current user is an assignee",
        "Response includes board name and column name for context",
        "Results ordered by dueDate ascending, nulls last"
      ]
    },
    {
      "id": "US-502",
      "title": "Today API: GET /api/v1/me/today — cards due today across all boards",
      "phase": "PHASE-005",
      "dependencies": [
        "US-203"
      ],
      "status": "done",
      "acceptance_criteria": [
        "GET /api/v1/me/today returns cards where dueDate equals today",
        "Only returns cards assigned to or created by current user",
        "Response includes board and column context"
      ]
    },
    {
      "id": "US-503",
      "title": "Upcoming API: GET /api/v1/me/upcoming — cards due in next 7 days",
      "phase": "PHASE-005",
      "dependencies": [
        "US-502"
      ],
      "status": "done",
      "acceptance_criteria": [
        "GET /api/v1/me/upcoming returns cards due within the next 7 days from today",
        "Excludes cards due today (covered by Today API)",
        "Results ordered by dueDate ascending"
      ]
    },
    {
      "id": "US-601",
      "title": "WorkspaceSwitcher component: display current workspace name with dropdown to switch",
      "phase": "PHASE-006",
      "dependencies": [
        "US-104",
        "US-402"
      ],
      "status": "done",
      "acceptance_criteria": [
        "WorkspaceSwitcher renders current workspace name in sidebar header",
        "Dropdown lists all workspaces the user belongs to",
        "Selecting a workspace updates the active workspace context",
        "Switching workspace reloads board list"
      ]
    },
    {
      "id": "US-602",
      "title": "Sidebar: starred boards section",
      "phase": "PHASE-006",
      "dependencies": [
        "US-402",
        "US-601"
      ],
      "status": "done",
      "acceptance_criteria": [
        "Sidebar shows Starred Boards section above All Boards",
        "Lists boards starred by current user with board name links",
        "Section hidden if no boards are starred",
        "Clicking a board navigates to board view"
      ]
    },
    {
      "id": "US-603",
      "title": "Sidebar: smart view nav items (Inbox, Today, Upcoming) with card counts",
      "phase": "PHASE-006",
      "dependencies": [
        "US-501",
        "US-502",
        "US-503",
        "US-602"
      ],
      "status": "done",
      "acceptance_criteria": [
        "Sidebar shows Inbox, Today, Upcoming navigation items",
        "Each item displays a badge with current card count",
        "Counts update on sidebar render",
        "Clicking navigates to corresponding view page"
      ]
    },
    {
      "id": "US-604",
      "title": "InboxView page: card list with board/column context",
      "phase": "PHASE-006",
      "dependencies": [
        "US-603"
      ],
      "status": "done",
      "acceptance_criteria": [
        "InboxView page renders at /inbox route",
        "Lists all assigned cards with card title, board name, column name",
        "Shows due date if present",
        "Empty state shown when no cards"
      ]
    },
    {
      "id": "US-605",
      "title": "TodayView and UpcomingView pages",
      "phase": "PHASE-006",
      "dependencies": [
        "US-603"
      ],
      "status": "done",
      "acceptance_criteria": [
        "TodayView page renders at /today route with cards due today",
        "UpcomingView page renders at /upcoming route with cards due in next 7 days",
        "Both pages show card title, board, column, and due date",
        "Empty state shown when no cards"
      ]
    },
    {
      "id": "US-606",
      "title": "Sidebar: boards grouped under workspace with task count",
      "phase": "PHASE-006",
      "dependencies": [
        "US-601",
        "US-603"
      ],
      "status": "done",
      "acceptance_criteria": [
        "All Boards section groups boards under their workspace name",
        "Each board row shows a task count badge",
        "Workspaces without boards show no board entries",
        "Board links navigate to board view"
      ]
    },
    {
      "id": "US-701",
      "title": "Timeline data endpoint: GET /api/v1/boards/{id}/timeline",
      "phase": "PHASE-007",
      "dependencies": [
        "US-204"
      ],
      "status": "done",
      "acceptance_criteria": [
        "GET /api/v1/boards/{id}/timeline returns all cards with startDate or dueDate",
        "Response includes id, title, startDate, dueDate, columnName, assignees",
        "Cards without both dates are excluded",
        "Returns 404 if board not found"
      ]
    },
    {
      "id": "US-702",
      "title": "TimelineView: horizontal date grid with month/week header",
      "phase": "PHASE-007",
      "dependencies": [
        "US-701"
      ],
      "status": "done",
      "acceptance_criteria": [
        "TimelineView renders at /boards/{id}/timeline route",
        "Horizontal scrollable grid shows days as columns",
        "Header row shows month labels and week numbers",
        "View spans at least 3 months from today"
      ]
    },
    {
      "id": "US-703",
      "title": "Timeline task bars: render colored bars per card spanning startDate to dueDate",
      "phase": "PHASE-007",
      "dependencies": [
        "US-702"
      ],
      "status": "done",
      "acceptance_criteria": [
        "Each card renders as a colored horizontal bar",
        "Bar spans from startDate column to dueDate column",
        "Bar is positioned in the row corresponding to the card",
        "Hovering bar shows card title tooltip"
      ]
    },
    {
      "id": "US-801",
      "title": "CalendarView: monthly grid with cards on due-date cells",
      "phase": "PHASE-008",
      "dependencies": [
        "US-104"
      ],
      "status": "done",
      "acceptance_criteria": [
        "CalendarView renders at /boards/{id}/calendar route",
        "Monthly grid shows 7-column week layout",
        "Cards appear on the cell matching their dueDate",
        "Card chips show card title, truncated if needed"
      ]
    },
    {
      "id": "US-802",
      "title": "CalendarView: month navigation (previous/next) and view toggle integration",
      "phase": "PHASE-008",
      "dependencies": [
        "US-801"
      ],
      "status": "done",
      "acceptance_criteria": [
        "Previous and Next buttons navigate between months",
        "Current month label updates on navigation",
        "View toggle allows switching between Board, Calendar, and Timeline views",
        "Active view is highlighted in the toggle"
      ]
    },
    {
      "id": "US-901",
      "title": "Swimlane toggle: group cards by label within each board column",
      "phase": "PHASE-009",
      "dependencies": [
        "US-601"
      ],
      "status": "done",
      "acceptance_criteria": [
        "Board header has a Swimlanes toggle button",
        "When enabled, cards in each column are grouped by label",
        "Each swimlane row shows the label name as a header",
        "Cards without a label appear in an Unlabeled swimlane"
      ]
    },
    {
      "id": "US-1001",
      "title": "Card detail: multi-assignee avatar stack display",
      "phase": "PHASE-010",
      "dependencies": [
        "US-203"
      ],
      "status": "done",
      "acceptance_criteria": [
        "Card detail modal shows stacked avatars for all assignees",
        "Avatar stack shows up to 3 avatars then +N overflow indicator",
        "Each avatar shows user initials or profile image",
        "Hovering an avatar shows user display name"
      ]
    },
    {
      "id": "US-1002",
      "title": "Card detail: assignee picker to add/remove multiple assignees",
      "phase": "PHASE-010",
      "dependencies": [
        "US-1001"
      ],
      "status": "done",
      "acceptance_criteria": [
        "Clicking the avatar stack opens an assignee picker dropdown",
        "Picker lists workspace members with checkboxes",
        "Checking a member calls add assignee API",
        "Unchecking a member calls remove assignee API"
      ]
    },
    {
      "id": "US-1003",
      "title": "Card detail: attachment upload UI (file picker and attachment list)",
      "phase": "PHASE-010",
      "dependencies": [
        "US-302",
        "US-1001"
      ],
      "status": "done",
      "acceptance_criteria": [
        "Card detail modal shows an Attachments section",
        "File picker button triggers file upload to POST /cards/{id}/attachments",
        "Uploaded attachments listed with filename and download link",
        "Upload progress indicator shown during upload"
      ]
    },
    {
      "id": "US-1004",
      "title": "Card detail: copy-link button copies shareable card URL to clipboard",
      "phase": "PHASE-010",
      "dependencies": [
        "US-1001"
      ],
      "status": "done",
      "acceptance_criteria": [
        "Card detail modal has a Copy Link button",
        "Clicking copies the full card URL to clipboard",
        "Button shows a checkmark confirmation for 2 seconds after copy",
        "URL navigates directly to the card when opened"
      ]
    },
    {
      "id": "US-1005",
      "title": "Board star toggle on board header and BoardCard",
      "phase": "PHASE-010",
      "dependencies": [
        "US-402",
        "US-602"
      ],
      "status": "done",
      "acceptance_criteria": [
        "Board header shows a star icon button",
        "BoardCard in boards list shows a star icon button",
        "Clicking star calls POST /boards/{id}/star or DELETE /boards/{id}/star",
        "Star icon reflects current starred state immediately (optimistic update)"
      ]
    },
    {
      "id": "US-1101",
      "title": "Mobile bottom navigation bar (Board, Today, Timeline, Inbox tabs)",
      "phase": "PHASE-011",
      "dependencies": [
        "US-604",
        "US-605"
      ],
      "status": "done",
      "acceptance_criteria": [
        "Bottom nav bar visible on screens narrower than 768px",
        "Four tabs: Board, Today, Timeline, Inbox",
        "Active tab is highlighted",
        "Tapping a tab navigates to the corresponding view"
      ]
    },
    {
      "id": "US-1102",
      "title": "Mobile board view: horizontal scrollable column tabs replacing desktop column layout",
      "phase": "PHASE-011",
      "dependencies": [
        "US-1101"
      ],
      "status": "done",
      "acceptance_criteria": [
        "On mobile, board columns are shown as tabs at the top",
        "Active column tab shows that column's cards below",
        "Tabs are horizontally scrollable if they overflow",
        "Desktop layout unchanged at 768px and above"
      ]
    },
    {
      "id": "US-1103",
      "title": "Mobile card layout: responsive CardItem and CardModal",
      "phase": "PHASE-011",
      "dependencies": [
        "US-1102",
        "US-1003"
      ],
      "status": "done",
      "acceptance_criteria": [
        "CardItem is full-width on mobile with touch-friendly tap target",
        "CardModal opens as a bottom sheet on mobile",
        "All card detail fields are accessible in the bottom sheet",
        "Desktop card modal behavior unchanged at 768px and above"
      ]
    }
  ],
  "summary": {
    "todo": 0,
    "in_progress": 0,
    "done": 35
  }
}